sintt.py
sintt-1.0.0.dist-info/METADATA
sintt-1.0.0.dist-info/WHEEL
sintt-1.0.0.dist-info/top_level.txt
sintt-1.0.0.dist-info/RECORD
